reequirements/__init__.py
reequirements/api.py
reequirements-1.2.1.dist-info/LICENSE
reequirements-1.2.1.dist-info/METADATA
reequirements-1.2.1.dist-info/WHEEL
reequirements-1.2.1.dist-info/top_level.txt
reequirements-1.2.1.dist-info/RECORD
