Metadata-Version: 2.1
Name: reequirements
Version: 1.2.1
Summary: Library for defining and checking for the status of requirements needed for your Python project
Home-page: https://github.com/zmarffy/reequirements
Author: Zeke Marffy
Author-email: zmarffy@yahoo.com
License: MIT
Platform: UNKNOWN
Requires-Python: >=3.3
